{"cameraMode":{"drawMode":0,"name":"Shaded","section":"Shading Mode"},"sceneLighting":true,"audioPlay":false,"sceneViewState":{"m_AlwaysRefresh":false,"showFog":true,"showSkybox":true,"showFlares":true,"showImageEffects":true,"showParticleSystems":true,"showVisualEffectGraphs":true,"m_FxEnabled":true},"in2DMode":false,"pivot":{"x":7.651956558227539,"y":-22.132577896118165,"z":-54.955528259277347},"rotation":{"x":0.28300178050994875,"y":0.05463288351893425,"z":-0.016149885952472688,"w":0.957443356513977},"size":18.91573143005371,"orthographic":false}